<?xml version="1.0" encoding="UTF-8" standalone="no"?><NikuDataBus xmlns:xsi="http://www.w3.org/2001/XMLSchema-instance" xsi:noNamespaceSchemaLocation="../xsd/nikuxog_contentPack.xsd">
      <Header action="write" externalSource="NIKU" objectType="contentPack" version="16.1.1.1485"/>
      <contentPack update="true">
        <lookups update="true">
          <dynamicLookup autoSuggestEnabled="true" autoSuggestMaxSuggestions="10" code="CSK_RPT_ROLE" displayAttributeName="resource_name" hiddenAttributeName="resource_key" objectCode="" sortAttributeName="resource_name" sortDirection="asc" source="niku.com" status="active" update="true">
            
            
            
            
            <nls description="Report (Resource Roles)" languageCode="en" name="Report (Resource Roles)"/>
            
            
            
            
            
            
            
            
            
            
            
            
            
            
            
            
            <nsql databaseId="Datawarehouse" dbVendor="all"><![CDATA[SELECT @SELECT:r.resource_key:resource_key@,
       @SELECT:r.resource_id:resource_id@,
       @SELECT:r.resource_name:resource_name@
FROM   dwh_res_resource r
WHERE  r.is_active = 1
AND    r.is_role = 1
AND    EXISTS (SELECT 1
               FROM   dwh_res_security_v
               WHERE  user_uid = @WHERE:PARAM:USER_UID@
               AND    resource_key = r.resource_key)
AND    @FILTER@]]></nsql>
            <displayedSuggestionAttributes>
              <displayedSuggestionAttribute value="resource_name"/>
            </displayedSuggestionAttributes>
            <searchedSuggestionAttributes>
              <searchedSuggestionAttribute value="resource_name"/>
            </searchedSuggestionAttributes>
            <browsePage>
              <singleSelectPageTitles>
                
                
                
                
                <nls description="No description" languageCode="en" name="Select Resource Role"/>
                
                
                
                
                
                
                
                
                
                
                
                
                
                
                
                
              </singleSelectPageTitles>
              <multiSelectPageTitles>
                
                
                
                
                <nls description="No description" languageCode="en" name="Select Resource Roles"/>
                
                
                
                
                
                
                
                
                
                
                
                
                
                
                
                
              </multiSelectPageTitles>
              <filter code="resource_id" defaultValue="" order="2" widgetType="text">
                
                
                
                
                <nls description="No description" languageCode="en" name="Role ID"/>
                
                
                
                
                
                
                
                
                
                
                
                
                
                
                
                
              </filter>
              <filter code="resource_name" defaultValue="" order="1" widgetType="text">
                
                
                
                
                <nls description="No description" languageCode="en" name="Role Name"/>
                
                
                
                
                
                
                
                
                
                
                
                
                
                
                
                
              </filter>
              <listColumn code="resource_key" order="1" widgetType="hidden">
                
                
                
                
                <nls description="No description" languageCode="en" name="Role Key"/>
                
                
                
                
                
                
                
                
                
                
                
                
                
                
                
                
              </listColumn>
              <listColumn code="resource_id" order="2" widgetType="text">
                
                
                
                
                <nls description="No description" languageCode="en" name="Role ID"/>
                
                
                
                
                
                
                
                
                
                
                
                
                
                
                
                
              </listColumn>
              <listColumn code="resource_name" order="1" widgetType="text">
                
                
                
                
                <nls description="No description" languageCode="en" name="Role Name"/>
                
                
                
                
                
                
                
                
                
                
                
                
                
                
                
                
              </listColumn>
            </browsePage>
          </dynamicLookup>
        </lookups>
      </contentPack>
      <XOGOutput>
        <Object type="contentPack"/>
        <Status state="SUCCESS"/>
        <Statistics failureRecords="0" insertedRecords="0" totalNumberOfRecords="1" updatedRecords="0"/>
        <Records/>
      </XOGOutput>
    </NikuDataBus>