<?xml version="1.0" encoding="UTF-8" standalone="no"?><NikuDataBus xmlns:xsi="http://www.w3.org/2001/XMLSchema-instance" xsi:noNamespaceSchemaLocation="../xsd/nikuxog_contentPack.xsd">
      <Header action="write" externalSource="NIKU" objectType="contentPack" version="16.1.2.1567"/>
      <contentPack update="true">
        <lookups update="true">
          <dynamicLookup autoSuggestEnabled="true" autoSuggestMaxSuggestions="10" code="DWH_TRD_TRENDS" displayAttributeName="trend_name" hiddenAttributeName="trend_key" objectCode="" sortAttributeName="trend_name" sortDirection="asc" source="niku.com" status="active" update="true">
            
            
            
            
            <nls description="Data Warehouse Trends" languageCode="en" name="Data Warehouse Trends"/>
            
            
            
            
            
            
            
            
            
            
            
            
            
            
            
            
            <nsql databaseId="Niku" dbVendor="mssql"><![CDATA[SELECT @SELECT:t.trend_key:trend_key@,
       @SELECT:t.trend_name:trend_name@,
       @SELECT:t.trend_year:trend_year@,
       @SELECT:l.name:trend_type@,
       @SELECT:l1.name:trend_period@,
       @SELECT:l.language_code:language_code@,
       @SELECT:t.created_date:created_date@,
       @SELECT:t.last_updated_date:last_updated_date@
FROM   dwh_trd_trend t,
       cmn_lookups_v l,
       cmn_lookups_v l1
WHERE  t.trend_type = l.lookup_code
AND    l.lookup_type = 'DWH_TRD_TYPE'
AND    l.language_code = @WHERE:PARAM:LANGUAGE@
AND    t.trend_period = l1.lookup_code
AND    l1.lookup_type = 'DWH_TRD_PERIODS'
AND    l1.language_code = @WHERE:PARAM:LANGUAGE@
AND    @FILTER@]]></nsql>
            <nsql databaseId="Niku" dbVendor="oracle"><![CDATA[SELECT @SELECT:t.trend_key:trend_key@,
       @SELECT:t.trend_name:trend_name@,
       @SELECT:t.trend_year:trend_year@,
       @SELECT:l.name:trend_type@,
       @SELECT:l1.name:trend_period@,
       @SELECT:l.language_code:language_code@,
       @SELECT:t.created_date:created_date@,
       @SELECT:t.last_updated_date:last_updated_date@
FROM   dwh_trd_trend t,
       cmn_lookups_v l,
       cmn_lookups_v l1
WHERE  t.trend_type = l.lookup_code
AND    l.lookup_type = 'DWH_TRD_TYPE'
AND    l.language_code = @WHERE:PARAM:LANGUAGE@
AND    t.trend_period = l1.lookup_code
AND    l1.lookup_type = 'DWH_TRD_PERIODS'
AND    l1.language_code = @WHERE:PARAM:LANGUAGE@
AND    @FILTER@]]></nsql>
            <nsql databaseId="Niku" dbVendor="postgres"><![CDATA[SELECT @SELECT:t.trend_key:trend_key@,
       @SELECT:t.trend_name:trend_name@,
       @SELECT:t.trend_year:trend_year@,
       @SELECT:l.name:trend_type@,
       @SELECT:l1.name:trend_period@,
       @SELECT:l.language_code:language_code@,
       @SELECT:t.created_date:created_date@,
       @SELECT:t.last_updated_date:last_updated_date@
FROM   dwh_trd_ppm_trends t,
       cmn_lookups_v l,
       cmn_lookups_v l1
WHERE  t.trend_type = l.lookup_code
AND    l.lookup_type = 'DWH_TRD_TYPE'
AND    l.language_code = @WHERE:PARAM:LANGUAGE@
AND    t.trend_period = l1.lookup_code
AND    l1.lookup_type = 'DWH_TRD_PERIODS'
AND    l1.language_code = @WHERE:PARAM:LANGUAGE@
AND    @FILTER@]]></nsql>
            <displayedSuggestionAttributes>
              <displayedSuggestionAttribute value="trend_name"/>
            </displayedSuggestionAttributes>
            <searchedSuggestionAttributes>
              <searchedSuggestionAttribute value="trend_name"/>
            </searchedSuggestionAttributes>
            <browsePage>
              <singleSelectPageTitles>
                
                
                
                
                <nls description="Trend Browse" languageCode="en" name="Trend Browse"/>
                
                
                
                
                
                
                
                
                
                
                
                
                
                
                
                
              </singleSelectPageTitles>
              <multiSelectPageTitles>
                
                
                
                
                <nls description="Trend Browse" languageCode="en" name="Trend Browse"/>
                
                
                
                
                
                
                
                
                
                
                
                
                
                
                
                
              </multiSelectPageTitles>
              <filter code="trend_name" defaultValue="" order="1" widgetType="text">
                
                
                
                
                <nls description="Trend Name" languageCode="en" name="Trend Name"/>
                
                
                
                
                
                
                
                
                
                
                
                
                
                
                
                
              </filter>
              <filter code="trend_year" defaultValue="" lookupCode="DWH_TRD_YEARS" order="2" widgetType="select">
                
                
                
                
                <nls description="Trend Year" languageCode="en" name="Trend Year"/>
                
                
                
                
                
                
                
                
                
                
                
                
                
                
                
                
              </filter>
              <filter code="trend_type" defaultValue="" lookupCode="DWH_TRD_TYPE" order="3" widgetType="select">
                
                
                
                
                <nls description="Trend Type" languageCode="en" name="Trend Type"/>
                
                
                
                
                
                
                
                
                
                
                
                
                
                
                
                
              </filter>
              <filter code="trend_period" defaultValue="" lookupCode="DWH_TRD_PERIODS" order="4" widgetType="select">
                
                
                
                
                <nls description="Trend Period" languageCode="en" name="Trend Period"/>
                
                
                
                
                
                
                
                
                
                
                
                
                
                
                
                
              </filter>
              <listColumn code="trend_key" order="1" widgetType="hidden">
                
                
                
                
                <nls description="trend_key" languageCode="en" name="trend_key"/>
                
                
                
                
                
                
                
                
                
                
                
                
                
                
                
                
              </listColumn>
              <listColumn code="trend_name" order="1" widgetType="text">
                
                
                
                
                <nls description="Trend Name" languageCode="en" name="Trend Name"/>
                
                
                
                
                
                
                
                
                
                
                
                
                
                
                
                
              </listColumn>
              <listColumn code="trend_year" order="2" widgetType="select">
                
                
                
                
                <nls description="Trend Year" languageCode="en" name="Trend Year"/>
                
                
                
                
                
                
                
                
                
                
                
                
                
                
                
                
              </listColumn>
              <listColumn code="trend_type" order="3" widgetType="select">
                
                
                
                
                <nls description="Trend Type" languageCode="en" name="Trend Type"/>
                
                
                
                
                
                
                
                
                
                
                
                
                
                
                
                
              </listColumn>
              <listColumn code="trend_period" order="4" widgetType="select">
                
                
                
                
                <nls description="Trend Period" languageCode="en" name="Trend Period"/>
                
                
                
                
                
                
                
                
                
                
                
                
                
                
                
                
              </listColumn>
              <listColumn code="created_date" order="5" widgetType="text">
                
                
                
                
                <nls description="Created Date" languageCode="en" name="Created Date"/>
                
                
                
                
                
                
                
                
                
                
                
                
                
                
                
                
              </listColumn>
              <listColumn code="last_updated_date" order="6" widgetType="text">
                
                
                
                
                <nls description="Last Updated Date" languageCode="en" name="Last Updated Date"/>
                
                
                
                
                
                
                
                
                
                
                
                
                
                
                
                
              </listColumn>
            </browsePage>
          </dynamicLookup>
        </lookups>
      </contentPack>
      <XOGOutput>
        <Object type="contentPack"/>
        <Status state="SUCCESS"/>
        <Statistics failureRecords="0" insertedRecords="0" totalNumberOfRecords="1" updatedRecords="0"/>
        <Records/>
      </XOGOutput>
    </NikuDataBus>