<?xml version="1.0" encoding="UTF-8" standalone="no"?><NikuDataBus xmlns:xsi="http://www.w3.org/2001/XMLSchema-instance" xsi:noNamespaceSchemaLocation="../xsd/nikuxog_contentPack.xsd">
      <Header action="write" externalSource="NIKU" objectType="contentPack" version="16.1.2.1567"/>
      <contentPack update="true">
        <lookups update="true">
          <dynamicLookup autoSuggestEnabled="true" autoSuggestMaxSuggestions="10" code="LOOKUP_BLP_AVIS_EXT" displayAttributeName="visual_id" hiddenAttributeName="visual_id" objectCode="" sortAttributeName="visual_id" sortDirection="asc" source="niku.com" status="active" update="true">
            
            
            
            
            <nls description="Blueprint external app available visual ids" languageCode="en" name="Blueprint External App Visuals"/>
            
            
            
            
            
            
            
            
            
            
            
            
            
            
            
            
            <nsql databaseId="Niku" dbVendor="all"><![CDATA[SELECT  @SELECT:bav.id:visual_id@
                    FROM blp_available_visuals bav,
                    blp_blueprint_visuals bbv
                    WHERE 1=1
                    AND bav.visual_type = 'externalapp'
                    AND bav.visual_category = 'MODULE'
                    AND bbv.available_visual_id = bav.id
                    AND bbv.blueprint_id = @WHERE:PARAM:USER_DEF:INTEGER:BLUEPRINT_ID@
                    AND @FILTER@]]></nsql>
            <displayedSuggestionAttributes>
              <displayedSuggestionAttribute value="visual_id"/>
            </displayedSuggestionAttributes>
            <searchedSuggestionAttributes>
              <searchedSuggestionAttribute value="visual_id"/>
            </searchedSuggestionAttributes>
            <browsePage>
              <singleSelectPageTitles>
                
                
                
                
                <nls description="LOOKUP_BLP_AVIS_EXT_01" languageCode="en" name="LOOKUP_BLP_AVIS_EXT_01"/>
                
                
                
                
                
                
                
                
                
                
                
                
                
                
                
                
              </singleSelectPageTitles>
              <multiSelectPageTitles>
                
                
                
                
                <nls description="LOOKUP_BLP_AVIS_EXT_01" languageCode="en" name="LOOKUP_BLP_AVIS_EXT_01"/>
                
                
                
                
                
                
                
                
                
                
                
                
                
                
                
                
              </multiSelectPageTitles>
              <filter code="visual_id" defaultValue="" order="1" widgetType="text">
                
                
                
                
                <nls description="Available Visual Id" languageCode="en" name="visual_id"/>
                
                
                
                
                
                
                
                
                
                
                
                
                
                
                
                
              </filter>
              <listColumn code="visual_id" order="1" widgetType="text">
                
                
                
                
                <nls description="Available Visual Id" languageCode="en" name="visual_id"/>
                
                
                
                
                
                
                
                
                
                
                
                
                
                
                
                
              </listColumn>
            </browsePage>
          </dynamicLookup>
        </lookups>
      </contentPack>
      <XOGOutput>
        <Object type="contentPack"/>
        <Status state="SUCCESS"/>
        <Statistics failureRecords="0" insertedRecords="0" totalNumberOfRecords="1" updatedRecords="0"/>
        <Records/>
      </XOGOutput>
    </NikuDataBus>