<?xml version="1.0" encoding="UTF-8" standalone="no"?><NikuDataBus xmlns:xsi="http://www.w3.org/2001/XMLSchema-instance" xsi:noNamespaceSchemaLocation="../xsd/nikuxog_contentPack.xsd">
      <Header action="write" externalSource="NIKU" objectType="contentPack" version="16.1.2.1567"/>
      <contentPack update="true">
        <lookups update="true">
          <staticLookup autoSuggestEnabled="true" autoSuggestMaxSuggestions="10" code="PRTIMEENTRY_USER_LOV1" hiddenAttributeName="lookup_code" sortStyle="alphanumeric" source="niku.com" status="active" update="true">
            
            
            
            
            <nls description="User defied lookups for time entries" languageCode="en" name="Time Entry User Lookup field 1"/>
            
            
            
            
            
            
            
            
            
            
            
            
            
            
            
            
            <lookupValue code="F1" enum="0" sortOrder="0" status="active">
              
              
              
              
              <nls description="Feature F1: Priority Fraud Alerts&#13;&#10;" languageCode="en" name="Feature F1: Priority Fraud Alerts"/>
              
              
              
              
              
              
              
              
              
              
              
              
              
              
              
              
            </lookupValue>
            <lookupValue code="F12" enum="0" sortOrder="0" status="active">
              
              
              
              
              <nls description="Feature F12: Integrate with PayPal&#13;&#10;" languageCode="en" name="Feature F12: Integrate with PayPal"/>
              
              
              
              
              
              
              
              
              
              
              
              
              
              
              
              
            </lookupValue>
            <lookupValue code="F14" enum="0" sortOrder="0" status="active">
              
              
              
              
              <nls description="Feature F14: Creation of security audit trail&#13;&#10;" languageCode="en" name="Feature F14: Creation of security audit trail"/>
              
              
              
              
              
              
              
              
              
              
              
              
              
              
              
              
            </lookupValue>
            <lookupValue code="F16" enum="0" sortOrder="0" status="active">
              
              
              
              
              <nls description="Feature F16: Nexgen history&#13;&#10;" languageCode="en" name="Feature F16: Nexgen history"/>
              
              
              
              
              
              
              
              
              
              
              
              
              
              
              
              
            </lookupValue>
            <lookupValue code="F2" enum="0" sortOrder="0" status="active">
              
              
              
              
              <nls description="Feature F2: Account Management&#13;&#10;" languageCode="en" name="Feature F2: Account Management"/>
              
              
              
              
              
              
              
              
              
              
              
              
              
              
              
              
            </lookupValue>
            <lookupValue code="F27" enum="0" sortOrder="0" status="active">
              
              
              
              
              <nls description="Feature F27: Security preferences&#13;&#10;" languageCode="en" name="Feature F27: Security preferences"/>
              
              
              
              
              
              
              
              
              
              
              
              
              
              
              
              
            </lookupValue>
            <lookupValue code="F4" enum="0" sortOrder="0" status="active">
              
              
              
              
              <nls description="Feature F4: Saving profile&#13;&#10;" languageCode="en" name="Feature F4: Saving profile"/>
              
              
              
              
              
              
              
              
              
              
              
              
              
              
              
              
            </lookupValue>
            <lookupValue code="F9" enum="0" sortOrder="0" status="active">
              
              
              
              
              <nls description="Feature F9: Setup and configuration&#13;&#10;" languageCode="en" name="Feature F9: Setup and configuration"/>
              
              
              
              
              
              
              
              
              
              
              
              
              
              
              
              
            </lookupValue>
            <displayedSuggestionAttributes>
              <displayedSuggestionAttribute value="name"/>
            </displayedSuggestionAttributes>
            <searchedSuggestionAttributes>
              <searchedSuggestionAttribute value="name"/>
            </searchedSuggestionAttributes>
          </staticLookup>
        </lookups>
      </contentPack>
      <XOGOutput>
        <Object type="contentPack"/>
        <Status state="SUCCESS"/>
        <Statistics failureRecords="0" insertedRecords="0" totalNumberOfRecords="1" updatedRecords="0"/>
        <Records/>
      </XOGOutput>
    </NikuDataBus>