<?xml version="1.0" encoding="UTF-8" standalone="no"?><NikuDataBus xmlns:xsi="http://www.w3.org/2001/XMLSchema-instance" xsi:noNamespaceSchemaLocation="../xsd/nikuxog_contentPack.xsd">
      <Header action="write" externalSource="NIKU" objectType="contentPack" version="16.1.2.1567"/>
      <contentPack update="true">
        <objects>
          <object code="resourcecredit" entityCodeAttribute="odf_entity_code" fiscalPeriodTypeAttribute="odf_period_type" pageInstanceType="CBK_RESOURCECREDIT_TABS" pageLayoutAttribute="page_layout" periodEndAttribute="odf_period_end" periodStartAttribute="odf_period_start" raiseEvents="true" source="niku.com" update="true">
            
            
            
            
            <nls description="The Resource Credit Object - Chargeback Credit" languageCode="en" name="Resource Credit"/>
            
            
            
            
            
            
            
            
            
            
            
            
            
            
            
            
            <customAttribute active="true" code="obj_description" column="obj_description" constant="false" currencyConnected="false" custom="true" dataSize="2000" dataType="string" editable="true" multiValued="false" partitionCode="NIKU.ROOT" partitionMode="PARTITION_AND_ANSTRS_DESDNTS" presenceRequired="false" private="false" required="false" unique="false" virtual="false">
              
              
              
              
              <nls description="Credit Rule Description" languageCode="en" name="Credit Rule Description"/>
              
              
              
              
              
              
              
              
              
              
              
              
              
              
              
              
            </customAttribute>
            <links objectCode="resourcecredit">
              <link action="SubPage.5002000.actionLink" active="true" code="resourcecredit.ResourceCreditUpdate.link" isObjectInstanceLink="false" partitionCode="NIKU.ROOT" partitionMode="PARTITION_ONLY" system="true">
                
                
                
                
                <nls description="Resource Credit SubPage Update Credit Rule link" languageCode="en" name="Resource Credit SubPage Update Credit Rule link"/>
                
                
                
                
                
                
                
                
                
                
                
                
                
                
                
                
                <linkParam dataRef="odf_pk" dataSource="data" paramCode="odf_pk"/>
                <linkParam dataRef="odf_pk" dataSource="data" paramCode="resourcecredit_id"/>
                <linkParam dataRef="resourcecredit" dataSource="static" paramCode="odf_code"/>
                <linkParam dataRef="ResourceCreditUpdate" dataSource="static" paramCode="odf_view"/>
                <linkParam dataRef="entity_id" dataSource="data" paramCode="entity_id"/>
              </link>
            </links>
            <displayMappings/>
            <scoreContributions/>
            <actions/>
            <capabilities/>
            <autonumbering>
              <attributeAutonumbering autonumbered="true" code="resource_credit_code">
                <schemes>
                  <scheme isActive="1" maxLength="50" partitionCode="NIKU.ROOT">
                    <segments>
                      <segment autoExtended="0" length="3" position="1" textValue="CREDIT" type="TEXT"/>
                      <segment autoExtended="1" length="5" position="2" startValue="1" type="NUMERIC"/>
                    </segments>
                  </scheme>
                </schemes>
              </attributeAutonumbering>
            </autonumbering>
            
          </object>
        </objects>
      </contentPack>
      <XOGOutput>
        <Object type="contentPack"/>
        <Status state="SUCCESS"/>
        <Statistics failureRecords="0" insertedRecords="0" totalNumberOfRecords="3" updatedRecords="0"/>
        <Records/>
      </XOGOutput>
    </NikuDataBus>