<ClarityDBTableQuery>
  <QueryResult code="PRJ_PROJECT_DEPENDS">
    <columns/>
    <constraints>
      <constraints code="PRJ_PROJECT_DEPENDS.PRJ_PROJECT_DEPENDS_PK">
        <table_name>PRJ_PROJECT_DEPENDS</table_name>
        <constraint_name>PRJ_PROJECT_DEPENDS_PK</constraint_name>
        <constraint_type>P</constraint_type>
        <status>ENABLED</status>
        <deferrable>NOT DEFERRABLE</deferrable>
        <deferred>IMMEDIATE</deferred>
        <validated>VALIDATED</validated>
        <index_name>PRJ_PROJECT_DEPENDS_PK</index_name>
      </constraints>
    </constraints>
    <indexes>
      <indexes code="PRJ_PROJECT_DEPENDS.PRJ_PROJECT_DEPENDS_N1">
        <columns>
          <columns code="PRJ_PROJECT_DEPENDS.PRINCIPAL_ID.PRJ_PROJECT_DEPENDS_N1">
            <table_name>PRJ_PROJECT_DEPENDS</table_name>
            <index_name>PRJ_PROJECT_DEPENDS_N1</index_name>
            <column_name>PRINCIPAL_ID</column_name>
            <column_position>1</column_position>
            <descend>ASC</descend>
          </columns>
        </columns>
        <table_name>PRJ_PROJECT_DEPENDS</table_name>
        <index_name>PRJ_PROJECT_DEPENDS_N1</index_name>
        <index_type>NORMAL</index_type>
        <uniqueness>NONUNIQUE</uniqueness>
        <tablespace_name>INDX_SMALL</tablespace_name>
        <status>VALID</status>
        <degree>1</degree>
        <logging>YES</logging>
        <dropped>NO</dropped>
      </indexes>
      <indexes code="PRJ_PROJECT_DEPENDS.PRJ_PROJECT_DEPENDS_N2">
        <columns>
          <columns code="PRJ_PROJECT_DEPENDS.DEPENDENT_ID.PRJ_PROJECT_DEPENDS_N2">
            <table_name>PRJ_PROJECT_DEPENDS</table_name>
            <index_name>PRJ_PROJECT_DEPENDS_N2</index_name>
            <column_name>DEPENDENT_ID</column_name>
            <column_position>1</column_position>
            <descend>ASC</descend>
          </columns>
        </columns>
        <table_name>PRJ_PROJECT_DEPENDS</table_name>
        <index_name>PRJ_PROJECT_DEPENDS_N2</index_name>
        <index_type>NORMAL</index_type>
        <uniqueness>NONUNIQUE</uniqueness>
        <tablespace_name>INDX_SMALL</tablespace_name>
        <status>VALID</status>
        <degree>1</degree>
        <logging>YES</logging>
        <dropped>NO</dropped>
      </indexes>
      <indexes code="PRJ_PROJECT_DEPENDS.PRJ_PROJECT_DEPENDS_PK">
        <columns>
          <columns code="PRJ_PROJECT_DEPENDS.ID.PRJ_PROJECT_DEPENDS_PK">
            <table_name>PRJ_PROJECT_DEPENDS</table_name>
            <index_name>PRJ_PROJECT_DEPENDS_PK</index_name>
            <column_name>ID</column_name>
            <column_position>1</column_position>
            <descend>ASC</descend>
          </columns>
        </columns>
        <table_name>PRJ_PROJECT_DEPENDS</table_name>
        <index_name>PRJ_PROJECT_DEPENDS_PK</index_name>
        <index_type>NORMAL</index_type>
        <uniqueness>UNIQUE</uniqueness>
        <tablespace_name>INDX_SMALL</tablespace_name>
        <status>VALID</status>
        <degree>1</degree>
        <logging>YES</logging>
        <dropped>NO</dropped>
      </indexes>
    </indexes>
    <tablespace_name>USERS_SMALL</tablespace_name>
    <status>VALID</status>
    <logging>YES</logging>
    <degree>         1</degree>
    <cache>    N</cache>
    <table_lock>ENABLED</table_lock>
    <partitioned>NO</partitioned>
    <dropped>NO</dropped>
  </QueryResult>
</ClarityDBTableQuery>
