<ClarityDBTableQuery>
  <QueryResult code="RPT_INV_HIERARCHY">
    <columns/>
    <constraints/>
    <indexes>
      <indexes code="RPT_INV_HIERARCHY.RPT_INV_HIERARCHY_N1">
        <columns>
          <columns code="RPT_INV_HIERARCHY.PARENT_ID.RPT_INV_HIERARCHY_N1">
            <table_name>RPT_INV_HIERARCHY</table_name>
            <index_name>RPT_INV_HIERARCHY_N1</index_name>
            <column_name>PARENT_ID</column_name>
            <column_position>1</column_position>
            <descend>ASC</descend>
          </columns>
        </columns>
        <table_name>RPT_INV_HIERARCHY</table_name>
        <index_name>RPT_INV_HIERARCHY_N1</index_name>
        <index_type>NORMAL</index_type>
        <uniqueness>NONUNIQUE</uniqueness>
        <tablespace_name>INDX_SMALL</tablespace_name>
        <status>VALID</status>
        <degree>1</degree>
        <logging>YES</logging>
        <dropped>NO</dropped>
      </indexes>
      <indexes code="RPT_INV_HIERARCHY.RPT_INV_HIERARCHY_N2">
        <columns>
          <columns code="RPT_INV_HIERARCHY.CHILD_ID.RPT_INV_HIERARCHY_N2">
            <table_name>RPT_INV_HIERARCHY</table_name>
            <index_name>RPT_INV_HIERARCHY_N2</index_name>
            <column_name>CHILD_ID</column_name>
            <column_position>1</column_position>
            <descend>ASC</descend>
          </columns>
        </columns>
        <table_name>RPT_INV_HIERARCHY</table_name>
        <index_name>RPT_INV_HIERARCHY_N2</index_name>
        <index_type>NORMAL</index_type>
        <uniqueness>NONUNIQUE</uniqueness>
        <tablespace_name>INDX_SMALL</tablespace_name>
        <status>VALID</status>
        <degree>1</degree>
        <logging>YES</logging>
        <dropped>NO</dropped>
      </indexes>
      <indexes code="RPT_INV_HIERARCHY.RPT_INV_HIERARCHY_N3">
        <columns>
          <columns code="RPT_INV_HIERARCHY.THE_LEVEL.RPT_INV_HIERARCHY_N3">
            <table_name>RPT_INV_HIERARCHY</table_name>
            <index_name>RPT_INV_HIERARCHY_N3</index_name>
            <column_name>THE_LEVEL</column_name>
            <column_position>1</column_position>
            <descend>ASC</descend>
          </columns>
        </columns>
        <table_name>RPT_INV_HIERARCHY</table_name>
        <index_name>RPT_INV_HIERARCHY_N3</index_name>
        <index_type>NORMAL</index_type>
        <uniqueness>NONUNIQUE</uniqueness>
        <tablespace_name>INDX_SMALL</tablespace_name>
        <status>VALID</status>
        <degree>1</degree>
        <logging>YES</logging>
        <dropped>NO</dropped>
      </indexes>
    </indexes>
    <tablespace_name>USERS_SMALL</tablespace_name>
    <status>VALID</status>
    <logging>YES</logging>
    <degree>         1</degree>
    <cache>    N</cache>
    <table_lock>ENABLED</table_lock>
    <partitioned>NO</partitioned>
    <dropped>NO</dropped>
  </QueryResult>
</ClarityDBTableQuery>
