<ClarityDBTableQuery>
  <QueryResult code="RSM_BOOK_MANAGER_OBS_MAP">
    <columns/>
    <constraints>
      <constraints code="RSM_BOOK_MANAGER_OBS_MAP.RSM_BOOK_MANAGER_OBS_MAP_PK">
        <table_name>RSM_BOOK_MANAGER_OBS_MAP</table_name>
        <constraint_name>RSM_BOOK_MANAGER_OBS_MAP_PK</constraint_name>
        <constraint_type>P</constraint_type>
        <status>ENABLED</status>
        <deferrable>NOT DEFERRABLE</deferrable>
        <deferred>IMMEDIATE</deferred>
        <validated>VALIDATED</validated>
        <index_name>RSM_BOOK_MANAGER_OBS_MAP_PK</index_name>
      </constraints>
    </constraints>
    <indexes>
      <indexes code="RSM_BOOK_MANAGER_OBS_MAP.RSM_BOOK_MANAGER_OBS_MAP_N1">
        <columns>
          <columns code="RSM_BOOK_MANAGER_OBS_MAP.ROLE_ID.RSM_BOOK_MANAGER_OBS_MAP_N1">
            <table_name>RSM_BOOK_MANAGER_OBS_MAP</table_name>
            <index_name>RSM_BOOK_MANAGER_OBS_MAP_N1</index_name>
            <column_name>ROLE_ID</column_name>
            <column_position>1</column_position>
            <descend>ASC</descend>
          </columns>
        </columns>
        <table_name>RSM_BOOK_MANAGER_OBS_MAP</table_name>
        <index_name>RSM_BOOK_MANAGER_OBS_MAP_N1</index_name>
        <index_type>NORMAL</index_type>
        <uniqueness>NONUNIQUE</uniqueness>
        <tablespace_name>INDX_SMALL</tablespace_name>
        <status>VALID</status>
        <degree>1</degree>
        <logging>YES</logging>
        <dropped>NO</dropped>
      </indexes>
      <indexes code="RSM_BOOK_MANAGER_OBS_MAP.RSM_BOOK_MANAGER_OBS_MAP_PK">
        <columns>
          <columns code="RSM_BOOK_MANAGER_OBS_MAP.ID.RSM_BOOK_MANAGER_OBS_MAP_PK">
            <table_name>RSM_BOOK_MANAGER_OBS_MAP</table_name>
            <index_name>RSM_BOOK_MANAGER_OBS_MAP_PK</index_name>
            <column_name>ID</column_name>
            <column_position>1</column_position>
            <descend>ASC</descend>
          </columns>
        </columns>
        <table_name>RSM_BOOK_MANAGER_OBS_MAP</table_name>
        <index_name>RSM_BOOK_MANAGER_OBS_MAP_PK</index_name>
        <index_type>NORMAL</index_type>
        <uniqueness>UNIQUE</uniqueness>
        <tablespace_name>INDX_SMALL</tablespace_name>
        <status>VALID</status>
        <degree>1</degree>
        <logging>YES</logging>
        <dropped>NO</dropped>
      </indexes>
      <indexes code="RSM_BOOK_MANAGER_OBS_MAP.RSM_BOOK_MANAGER_OBS_MAP_U1">
        <columns>
          <columns code="RSM_BOOK_MANAGER_OBS_MAP.BOOK_MANAGER_ID.RSM_BOOK_MANAGER_OBS_MAP_U1">
            <table_name>RSM_BOOK_MANAGER_OBS_MAP</table_name>
            <index_name>RSM_BOOK_MANAGER_OBS_MAP_U1</index_name>
            <column_name>BOOK_MANAGER_ID</column_name>
            <column_position>3</column_position>
            <descend>ASC</descend>
          </columns>
          <columns code="RSM_BOOK_MANAGER_OBS_MAP.OBSUNIT_ID.RSM_BOOK_MANAGER_OBS_MAP_U1">
            <table_name>RSM_BOOK_MANAGER_OBS_MAP</table_name>
            <index_name>RSM_BOOK_MANAGER_OBS_MAP_U1</index_name>
            <column_name>OBSUNIT_ID</column_name>
            <column_position>2</column_position>
            <descend>ASC</descend>
          </columns>
          <columns code="RSM_BOOK_MANAGER_OBS_MAP.ROLE_ID.RSM_BOOK_MANAGER_OBS_MAP_U1">
            <table_name>RSM_BOOK_MANAGER_OBS_MAP</table_name>
            <index_name>RSM_BOOK_MANAGER_OBS_MAP_U1</index_name>
            <column_name>ROLE_ID</column_name>
            <column_position>1</column_position>
            <descend>ASC</descend>
          </columns>
        </columns>
        <table_name>RSM_BOOK_MANAGER_OBS_MAP</table_name>
        <index_name>RSM_BOOK_MANAGER_OBS_MAP_U1</index_name>
        <index_type>NORMAL</index_type>
        <uniqueness>UNIQUE</uniqueness>
        <tablespace_name>INDX_SMALL</tablespace_name>
        <status>VALID</status>
        <degree>1</degree>
        <logging>YES</logging>
        <dropped>NO</dropped>
      </indexes>
    </indexes>
    <tablespace_name>USERS_SMALL</tablespace_name>
    <status>VALID</status>
    <logging>YES</logging>
    <degree>         1</degree>
    <cache>    N</cache>
    <table_lock>ENABLED</table_lock>
    <partitioned>NO</partitioned>
    <dropped>NO</dropped>
  </QueryResult>
</ClarityDBTableQuery>
