{
  "_internalId" : 5050094,
  "associatedObject" : null,
  "associatedObjectType" : "inv",
  "canvas" : null,
  "classifier" : null,
  "listColumns" : [ {
    "_internalId" : 5057788,
    "listColumn" : {
      "_internalId" : 5057788,
      "_parent" : "http://clarityppm-demo7.capture.eu/ppm/rest/v1/private/views/5050094",
      "_self" : "http://clarityppm-demo7.capture.eu/ppm/rest/v1/private/views/5050094/listColumns/5057788",
      "aggregations" : null,
      "groupByPosition" : null,
      "groupType" : null,
      "isExcluded" : false,
      "isGrouped" : null,
      "isSelected" : false,
      "isVirtual" : null,
      "layout" : "grid",
      "metadataURL" : "lastUpdatedDate",
      "name" : "Last Updated Date",
      "pinned" : null,
      "position" : -999,
      "sortOrder" : null,
      "sortPosition" : null,
      "width" : null
    }
  }, {
    "_internalId" : 5057789,
    "listColumn" : {
      "_internalId" : 5057789,
      "_parent" : "http://clarityppm-demo7.capture.eu/ppm/rest/v1/private/views/5050094",
      "_self" : "http://clarityppm-demo7.capture.eu/ppm/rest/v1/private/views/5050094/listColumns/5057789",
      "aggregations" : null,
      "groupByPosition" : null,
      "groupType" : null,
      "isExcluded" : false,
      "isGrouped" : null,
      "isSelected" : false,
      "isVirtual" : null,
      "layout" : "grid",
      "metadataURL" : "impactDate",
      "name" : "impactDate",
      "pinned" : null,
      "position" : -999,
      "sortOrder" : null,
      "sortPosition" : null,
      "width" : null
    }
  }, {
    "_internalId" : 5057790,
    "listColumn" : {
      "_internalId" : 5057790,
      "_parent" : "http://clarityppm-demo7.capture.eu/ppm/rest/v1/private/views/5050094",
      "_self" : "http://clarityppm-demo7.capture.eu/ppm/rest/v1/private/views/5050094/listColumns/5057790",
      "aggregations" : null,
      "groupByPosition" : null,
      "groupType" : null,
      "isExcluded" : false,
      "isGrouped" : null,
      "isSelected" : true,
      "isVirtual" : null,
      "layout" : "grid",
      "metadataURL" : "hasConversations",
      "name" : "Conversation",
      "pinned" : "left",
      "position" : 1,
      "sortOrder" : null,
      "sortPosition" : null,
      "width" : 154
    }
  }, {
    "_internalId" : 5057791,
    "listColumn" : {
      "_internalId" : 5057791,
      "_parent" : "http://clarityppm-demo7.capture.eu/ppm/rest/v1/private/views/5050094",
      "_self" : "http://clarityppm-demo7.capture.eu/ppm/rest/v1/private/views/5050094/listColumns/5057791",
      "aggregations" : null,
      "groupByPosition" : null,
      "groupType" : null,
      "isExcluded" : false,
      "isGrouped" : null,
      "isSelected" : true,
      "isVirtual" : null,
      "layout" : "grid",
      "metadataURL" : "name",
      "name" : "Issue Name",
      "pinned" : null,
      "position" : 2,
      "sortOrder" : "asc",
      "sortPosition" : 1,
      "width" : 404
    }
  }, {
    "_internalId" : 5057792,
    "listColumn" : {
      "_internalId" : 5057792,
      "_parent" : "http://clarityppm-demo7.capture.eu/ppm/rest/v1/private/views/5050094",
      "_self" : "http://clarityppm-demo7.capture.eu/ppm/rest/v1/private/views/5050094/listColumns/5057792",
      "aggregations" : null,
      "groupByPosition" : null,
      "groupType" : null,
      "isExcluded" : false,
      "isGrouped" : null,
      "isSelected" : true,
      "isVirtual" : null,
      "layout" : "grid",
      "metadataURL" : "categoryType",
      "name" : "Category",
      "pinned" : null,
      "position" : 3,
      "sortOrder" : null,
      "sortPosition" : null,
      "width" : 199
    }
  }, {
    "_internalId" : 5057793,
    "listColumn" : {
      "_internalId" : 5057793,
      "_parent" : "http://clarityppm-demo7.capture.eu/ppm/rest/v1/private/views/5050094",
      "_self" : "http://clarityppm-demo7.capture.eu/ppm/rest/v1/private/views/5050094/listColumns/5057793",
      "aggregations" : null,
      "groupByPosition" : null,
      "groupType" : null,
      "isExcluded" : false,
      "isGrouped" : null,
      "isSelected" : true,
      "isVirtual" : null,
      "layout" : "grid",
      "metadataURL" : "priority",
      "name" : "Priority",
      "pinned" : null,
      "position" : 4,
      "sortOrder" : null,
      "sortPosition" : null,
      "width" : null
    }
  }, {
    "_internalId" : 5057794,
    "listColumn" : {
      "_internalId" : 5057794,
      "_parent" : "http://clarityppm-demo7.capture.eu/ppm/rest/v1/private/views/5050094",
      "_self" : "http://clarityppm-demo7.capture.eu/ppm/rest/v1/private/views/5050094/listColumns/5057794",
      "aggregations" : null,
      "groupByPosition" : null,
      "groupType" : null,
      "isExcluded" : false,
      "isGrouped" : null,
      "isSelected" : true,
      "isVirtual" : null,
      "layout" : "grid",
      "metadataURL" : "status",
      "name" : "Status",
      "pinned" : null,
      "position" : 5,
      "sortOrder" : null,
      "sortPosition" : null,
      "width" : 115
    }
  }, {
    "_internalId" : 5057795,
    "listColumn" : {
      "_internalId" : 5057795,
      "_parent" : "http://clarityppm-demo7.capture.eu/ppm/rest/v1/private/views/5050094",
      "_self" : "http://clarityppm-demo7.capture.eu/ppm/rest/v1/private/views/5050094/listColumns/5057795",
      "aggregations" : null,
      "groupByPosition" : null,
      "groupType" : null,
      "isExcluded" : false,
      "isGrouped" : null,
      "isSelected" : true,
      "isVirtual" : null,
      "layout" : "grid",
      "metadataURL" : "assignedTo",
      "name" : "Owner",
      "pinned" : null,
      "position" : 6,
      "sortOrder" : null,
      "sortPosition" : null,
      "width" : 174
    }
  }, {
    "_internalId" : 5057796,
    "listColumn" : {
      "_internalId" : 5057796,
      "_parent" : "http://clarityppm-demo7.capture.eu/ppm/rest/v1/private/views/5050094",
      "_self" : "http://clarityppm-demo7.capture.eu/ppm/rest/v1/private/views/5050094/listColumns/5057796",
      "aggregations" : null,
      "groupByPosition" : null,
      "groupType" : null,
      "isExcluded" : false,
      "isGrouped" : null,
      "isSelected" : true,
      "isVirtual" : null,
      "layout" : "grid",
      "metadataURL" : "targetResolutionDate",
      "name" : "Target Resolution Date",
      "pinned" : null,
      "position" : 7,
      "sortOrder" : null,
      "sortPosition" : null,
      "width" : 179
    }
  }, {
    "_internalId" : 5057797,
    "listColumn" : {
      "_internalId" : 5057797,
      "_parent" : "http://clarityppm-demo7.capture.eu/ppm/rest/v1/private/views/5050094",
      "_self" : "http://clarityppm-demo7.capture.eu/ppm/rest/v1/private/views/5050094/listColumns/5057797",
      "aggregations" : null,
      "groupByPosition" : null,
      "groupType" : null,
      "isExcluded" : false,
      "isGrouped" : null,
      "isSelected" : true,
      "isVirtual" : null,
      "layout" : "grid",
      "metadataURL" : "resolution",
      "name" : "Resolution",
      "pinned" : null,
      "position" : 8,
      "sortOrder" : null,
      "sortPosition" : null,
      "width" : null
    }
  }, {
    "_internalId" : 5057798,
    "listColumn" : {
      "_internalId" : 5057798,
      "_parent" : "http://clarityppm-demo7.capture.eu/ppm/rest/v1/private/views/5050094",
      "_self" : "http://clarityppm-demo7.capture.eu/ppm/rest/v1/private/views/5050094/listColumns/5057798",
      "aggregations" : null,
      "groupByPosition" : null,
      "groupType" : null,
      "isExcluded" : false,
      "isGrouped" : null,
      "isSelected" : true,
      "isVirtual" : null,
      "layout" : "grid",
      "metadataURL" : "resolvedBy",
      "name" : "Resolved By",
      "pinned" : null,
      "position" : 9,
      "sortOrder" : null,
      "sortPosition" : null,
      "width" : null
    }
  }, {
    "_internalId" : 5057799,
    "listColumn" : {
      "_internalId" : 5057799,
      "_parent" : "http://clarityppm-demo7.capture.eu/ppm/rest/v1/private/views/5050094",
      "_self" : "http://clarityppm-demo7.capture.eu/ppm/rest/v1/private/views/5050094/listColumns/5057799",
      "aggregations" : null,
      "groupByPosition" : null,
      "groupType" : null,
      "isExcluded" : false,
      "isGrouped" : null,
      "isSelected" : true,
      "isVirtual" : null,
      "layout" : "grid",
      "metadataURL" : "resolvedDate",
      "name" : "Resolved Date",
      "pinned" : null,
      "position" : 10,
      "sortOrder" : null,
      "sortPosition" : null,
      "width" : 161
    }
  }, {
    "_internalId" : 5057800,
    "listColumn" : {
      "_internalId" : 5057800,
      "_parent" : "http://clarityppm-demo7.capture.eu/ppm/rest/v1/private/views/5050094",
      "_self" : "http://clarityppm-demo7.capture.eu/ppm/rest/v1/private/views/5050094/listColumns/5057800",
      "aggregations" : null,
      "groupByPosition" : null,
      "groupType" : null,
      "isExcluded" : false,
      "isGrouped" : null,
      "isSelected" : true,
      "isVirtual" : null,
      "layout" : "grid",
      "metadataURL" : "isIncludedInStatusReporting",
      "name" : "isIncludedInStatusReporting",
      "pinned" : null,
      "position" : 11,
      "sortOrder" : null,
      "sortPosition" : null,
      "width" : null
    }
  } ],
  "name" : "(Copy) Default View",
  "picklistContexts" : [ {
    "_internalId" : 5020012,
    "pickListContext" : {
      "_internalId" : 5020012,
      "_self" : "http://clarityppm-demo7.capture.eu/ppm/rest/v1/private/picklistContexts/5020012",
      "code" : "issues",
      "instanceId" : null,
      "isActive" : true,
      "isPurged" : false,
      "name" : "issue",
      "objectCode" : "issue",
      "resourceName" : null,
      "userId" : null
    },
    "picklists" : [ ]
  } ],
  "type" : "issues",
  "uiViewBlueprint" : {
    "_internalId" : 5044054,
    "sections" : [ {
      "_internalId" : 5044140,
      "fields" : [ {
        "_internalId" : 5048079,
        "field" : {
          "_internalId" : 5048079,
          "_parent" : "http://clarityppm-demo7.capture.eu/ppm/rest/v1/private/uiViewBlueprints/5044054/sections/5044140",
          "_self" : "http://clarityppm-demo7.capture.eu/ppm/rest/v1/private/uiViewBlueprints/5044054/sections/5044140/fields/5048079",
          "column" : 0,
          "height" : 1,
          "metadataURL" : "hasConversation",
          "name" : "hasConversation",
          "row" : 0,
          "sectionId" : 5044140,
          "width" : 1
        }
      }, {
        "_internalId" : 5048080,
        "field" : {
          "_internalId" : 5048080,
          "_parent" : "http://clarityppm-demo7.capture.eu/ppm/rest/v1/private/uiViewBlueprints/5044054/sections/5044140",
          "_self" : "http://clarityppm-demo7.capture.eu/ppm/rest/v1/private/uiViewBlueprints/5044054/sections/5044140/fields/5048080",
          "column" : 1,
          "height" : 1,
          "metadataURL" : "name",
          "name" : "name",
          "row" : 0,
          "sectionId" : 5044140,
          "width" : 1
        }
      }, {
        "_internalId" : 5048081,
        "field" : {
          "_internalId" : 5048081,
          "_parent" : "http://clarityppm-demo7.capture.eu/ppm/rest/v1/private/uiViewBlueprints/5044054/sections/5044140",
          "_self" : "http://clarityppm-demo7.capture.eu/ppm/rest/v1/private/uiViewBlueprints/5044054/sections/5044140/fields/5048081",
          "column" : 0,
          "height" : 1,
          "metadataURL" : "categoryType",
          "name" : "categoryType",
          "row" : 1,
          "sectionId" : 5044140,
          "width" : 1
        }
      }, {
        "_internalId" : 5048082,
        "field" : {
          "_internalId" : 5048082,
          "_parent" : "http://clarityppm-demo7.capture.eu/ppm/rest/v1/private/uiViewBlueprints/5044054/sections/5044140",
          "_self" : "http://clarityppm-demo7.capture.eu/ppm/rest/v1/private/uiViewBlueprints/5044054/sections/5044140/fields/5048082",
          "column" : 1,
          "height" : 1,
          "metadataURL" : "priority",
          "name" : "priority",
          "row" : 1,
          "sectionId" : 5044140,
          "width" : 1
        }
      }, {
        "_internalId" : 5048083,
        "field" : {
          "_internalId" : 5048083,
          "_parent" : "http://clarityppm-demo7.capture.eu/ppm/rest/v1/private/uiViewBlueprints/5044054/sections/5044140",
          "_self" : "http://clarityppm-demo7.capture.eu/ppm/rest/v1/private/uiViewBlueprints/5044054/sections/5044140/fields/5048083",
          "column" : 0,
          "height" : 1,
          "metadataURL" : "status",
          "name" : "status",
          "row" : 2,
          "sectionId" : 5044140,
          "width" : 1
        }
      }, {
        "_internalId" : 5048084,
        "field" : {
          "_internalId" : 5048084,
          "_parent" : "http://clarityppm-demo7.capture.eu/ppm/rest/v1/private/uiViewBlueprints/5044054/sections/5044140",
          "_self" : "http://clarityppm-demo7.capture.eu/ppm/rest/v1/private/uiViewBlueprints/5044054/sections/5044140/fields/5048084",
          "column" : 1,
          "height" : 1,
          "metadataURL" : "assignedTo",
          "name" : "assignedTo",
          "row" : 2,
          "sectionId" : 5044140,
          "width" : 1
        }
      }, {
        "_internalId" : 5048085,
        "field" : {
          "_internalId" : 5048085,
          "_parent" : "http://clarityppm-demo7.capture.eu/ppm/rest/v1/private/uiViewBlueprints/5044054/sections/5044140",
          "_self" : "http://clarityppm-demo7.capture.eu/ppm/rest/v1/private/uiViewBlueprints/5044054/sections/5044140/fields/5048085",
          "column" : 0,
          "height" : 1,
          "metadataURL" : "targetResolutionDate",
          "name" : "targetResolutionDate",
          "row" : 3,
          "sectionId" : 5044140,
          "width" : 1
        }
      }, {
        "_internalId" : 5048086,
        "field" : {
          "_internalId" : 5048086,
          "_parent" : "http://clarityppm-demo7.capture.eu/ppm/rest/v1/private/uiViewBlueprints/5044054/sections/5044140",
          "_self" : "http://clarityppm-demo7.capture.eu/ppm/rest/v1/private/uiViewBlueprints/5044054/sections/5044140/fields/5048086",
          "column" : 1,
          "height" : 1,
          "metadataURL" : "impactDate",
          "name" : "impactDate",
          "row" : 3,
          "sectionId" : 5044140,
          "width" : 1
        }
      }, {
        "_internalId" : 5048087,
        "field" : {
          "_internalId" : 5048087,
          "_parent" : "http://clarityppm-demo7.capture.eu/ppm/rest/v1/private/uiViewBlueprints/5044054/sections/5044140",
          "_self" : "http://clarityppm-demo7.capture.eu/ppm/rest/v1/private/uiViewBlueprints/5044054/sections/5044140/fields/5048087",
          "column" : 0,
          "height" : 1,
          "metadataURL" : "resolution",
          "name" : "resolution",
          "row" : 4,
          "sectionId" : 5044140,
          "width" : 1
        }
      }, {
        "_internalId" : 5048088,
        "field" : {
          "_internalId" : 5048088,
          "_parent" : "http://clarityppm-demo7.capture.eu/ppm/rest/v1/private/uiViewBlueprints/5044054/sections/5044140",
          "_self" : "http://clarityppm-demo7.capture.eu/ppm/rest/v1/private/uiViewBlueprints/5044054/sections/5044140/fields/5048088",
          "column" : 1,
          "height" : 1,
          "metadataURL" : "resolvedDate",
          "name" : "resolvedDate",
          "row" : 4,
          "sectionId" : 5044140,
          "width" : 1
        }
      }, {
        "_internalId" : 5048089,
        "field" : {
          "_internalId" : 5048089,
          "_parent" : "http://clarityppm-demo7.capture.eu/ppm/rest/v1/private/uiViewBlueprints/5044054/sections/5044140",
          "_self" : "http://clarityppm-demo7.capture.eu/ppm/rest/v1/private/uiViewBlueprints/5044054/sections/5044140/fields/5048089",
          "column" : 1,
          "height" : 1,
          "metadataURL" : "resolvedBy",
          "name" : "resolvedBy",
          "row" : 5,
          "sectionId" : 5044140,
          "width" : 1
        }
      }, {
        "_internalId" : 5048090,
        "field" : {
          "_internalId" : 5048090,
          "_parent" : "http://clarityppm-demo7.capture.eu/ppm/rest/v1/private/uiViewBlueprints/5044054/sections/5044140",
          "_self" : "http://clarityppm-demo7.capture.eu/ppm/rest/v1/private/uiViewBlueprints/5044054/sections/5044140/fields/5048090",
          "column" : 0,
          "height" : 1,
          "metadataURL" : "isIncludedInStatusReporting",
          "name" : "isIncludedInStatusReporting",
          "row" : 6,
          "sectionId" : 5044140,
          "width" : 1
        }
      } ],
      "section" : {
        "_internalId" : 5044140,
        "_parent" : "http://clarityppm-demo7.capture.eu/ppm/rest/v1/private/uiViewBlueprints/5044054",
        "_self" : "http://clarityppm-demo7.capture.eu/ppm/rest/v1/private/uiViewBlueprints/5044054/sections/5044140",
        "blueprintId" : 5044054,
        "classifier" : null,
        "fields" : {
          "_self" : "http://clarityppm-demo7.capture.eu/ppm/rest/v1/private/uiViewBlueprints/5044054/sections/5044140/fields"
        },
        "name" : "uiViewSection",
        "sequence" : 1
      }
    } ],
    "uiViewBlueprint" : {
      "_internalId" : 5044054,
      "_links" : {
        "uiView" : "http://clarityppm-demo7.capture.eu/ppm/rest/v1/lookups/LOOKUP_UI_VIEWS/lookupValues"
      },
      "_self" : "http://clarityppm-demo7.capture.eu/ppm/rest/v1/private/uiViewBlueprints/5044054",
      "code" : "uiViewBlueprint5050095",
      "lastUpdatedBy" : "Lewis, Dana",
      "lastUpdatedDate" : "2022-02-28T07:47:23",
      "name" : "uiViewBlueprint5050095",
      "sections" : {
        "_self" : "http://clarityppm-demo7.capture.eu/ppm/rest/v1/private/uiViewBlueprints/5044054/sections"
      },
      "uiView" : {
        "_type" : "lookup",
        "displayValue" : "(Copy) Default View",
        "id" : "5050094"
      },
      "width" : 0.33
    }
  },
  "view" : {
    "_internalId" : 5050094,
    "_isFavorite" : false,
    "_links" : {
      "childViews" : "http://clarityppm-demo7.capture.eu/ppm/rest/v1/lookups/UI_VIEW_LOOKUP/lookupValues",
      "isShared" : "http://clarityppm-demo7.capture.eu/ppm/rest/v1/lookups/LOOKUP_VIEW_SHARE_TYPE/lookupValues",
      "mode" : "http://clarityppm-demo7.capture.eu/ppm/rest/v1/lookups/VIEW_MODE/lookupValues",
      "owner" : "http://clarityppm-demo7.capture.eu/ppm/rest/v1/lookups/LOOKUP_USER_ACTIVE_NO_SEC/lookupValues"
    },
    "_self" : "http://clarityppm-demo7.capture.eu/ppm/rest/v1/private/views/5050094",
    "associatedId" : null,
    "associatedObjectType" : "inv",
    "blueprintId" : 1,
    "childViews" : null,
    "classifier" : null,
    "defaultSort" : "name:asc,name:asc,name:asc",
    "groupSort" : "3_OTHER",
    "hasAccess" : false,
    "isDefault" : false,
    "isShared" : {
      "_type" : "lookup",
      "displayValue" : "Private",
      "id" : "SHARED_NONE"
    },
    "isSystem" : false,
    "lastUpdatedDate" : "2022-02-28T07:47:23",
    "listColumns" : {
      "_self" : "http://clarityppm-demo7.capture.eu/ppm/rest/v1/private/views/5050094/listColumns"
    },
    "mode" : {
      "_type" : "lookup",
      "displayValue" : "Saved",
      "id" : "SAVED"
    },
    "name" : "(Copy) Default View",
    "owner" : {
      "_type" : "lookup",
      "displayValue" : "Lewis, Dana",
      "id" : "5003008"
    },
    "position" : -1,
    "sharedGroupName" : null,
    "sharedPersonName" : null,
    "sharedWithGroup" : 0,
    "sharedWithPerson" : 0,
    "type" : "issues",
    "uiViewBlueprintId" : 5044054,
    "viewSettings" : {
      "_self" : "http://clarityppm-demo7.capture.eu/ppm/rest/v1/private/views/5050094/viewSettings"
    },
    "viewShare" : {
      "_self" : "http://clarityppm-demo7.capture.eu/ppm/rest/v1/private/views/5050094/viewShare"
    },
    "viewTargetId" : null,
    "visualWidgetConfigs" : {
      "_self" : "http://clarityppm-demo7.capture.eu/ppm/rest/v1/private/views/5050094/visualWidgetConfigs"
    }
  },
  "viewSettings" : [ {
    "_internalId" : 5045644,
    "viewSetting" : {
      "_internalId" : 5045644,
      "_links" : {
        "settingsMetadataId" : "http://clarityppm-demo7.capture.eu/ppm/rest/v1/lookups/LOOKUP_UI_SETTINGS_MD/lookupValues"
      },
      "_parent" : "http://clarityppm-demo7.capture.eu/ppm/rest/v1/private/views/5050094",
      "_self" : "http://clarityppm-demo7.capture.eu/ppm/rest/v1/private/views/5050094/viewSettings/5045644",
      "classifier" : null,
      "layout" : "layout",
      "name" : "current",
      "settingsMetadataId" : null,
      "value" : "grid"
    }
  } ],
  "visualWidgetConfigs" : [ ]
}